task_ruleset/__init__.py
task_ruleset-0.0.4.dist-info/METADATA
task_ruleset-0.0.4.dist-info/WHEEL
task_ruleset-0.0.4.dist-info/top_level.txt
task_ruleset-0.0.4.dist-info/RECORD
