Metadata-Version: 2.1
Name: task-ruleset
Version: 0.0.4
Summary: A scheduler for task and ruleset based parallel computation. Useful for highly parallel applications.
Home-page: https://github.com/venunathan12/task-ruleset
Author: Venu Nathan
Author-email: venunathan12@gmail.com
License: MIT
